edubot/__init__.py
edubot/bot.py
edubot/sql.py
edubot/types.py
edubot-0.7.6.dist-info/LICENSE
edubot-0.7.6.dist-info/METADATA
edubot-0.7.6.dist-info/WHEEL
edubot-0.7.6.dist-info/RECORD
