Metadata-Version: 2.1
Name: edubot
Version: 0.7.6
Summary: Basic Edubot module
License: GPLv3
Author: exciteabletom
Author-email: tom@digitalnook.net
Requires-Python: >=3.10,<4.0
Classifier: License :: Other/Proprietary License
Classifier: Programming Language :: Python :: 3
Classifier: Programming Language :: Python :: 3.10
Classifier: Programming Language :: Python :: 3.11
Classifier: Programming Language :: Python :: 3.12
Requires-Dist: beautifulsoup4 (>=4.12.2,<5.0.0)
Requires-Dist: langchain (>=0.0.279,<0.0.280)
Requires-Dist: openai (>=0.27.6,<0.28.0)
Requires-Dist: pillow (>=9.5.0,<10.0.0)
Requires-Dist: replicate (>=0.8.1,<0.9.0)
Requires-Dist: sqlalchemy[mypy] (>=2.0.14,<3.0.0)
Requires-Dist: stability-sdk (>=0.8.1,<0.9.0)
Requires-Dist: tiktoken (>=0.4.0,<0.5.0)
Requires-Dist: trafilatura (>=1.6.0,<2.0.0)
